precondition/__init__.py
precondition/distributed_shampoo.py
precondition/distributed_shampoo_test.py
precondition/precondition_test.py
precondition/quantization_utils.py
precondition/sm3.py
precondition/sm3_test.py
precondition_opt-0.3.0.dist-info/LICENSE
precondition_opt-0.3.0.dist-info/WHEEL
precondition_opt-0.3.0.dist-info/METADATA
precondition_opt-0.3.0.dist-info/RECORD
