Metadata-Version: 2.1
Name: precondition-opt
Version: 0.3.0
Summary: Preconditioning optimizers.
Keywords: 
Author-email: precondition authors <precondition-optimizers@google.com>
Requires-Python: >=3.8
Classifier: Programming Language :: Python :: 3
Classifier: Programming Language :: Python :: 3 :: Only
Classifier: License :: OSI Approved :: Apache Software License
Classifier: Intended Audience :: Science/Research
Requires-Dist: absl-py>=0.8.1 ; extra == "dev"
Requires-Dist: chex ; extra == "dev"
Requires-Dist: flax ; extra == "dev"
Requires-Dist: optax ; extra == "dev"
Requires-Dist: pytest ; extra == "dev"
Requires-Dist: pytest-xdist ; extra == "dev"
Requires-Dist: pylint>=2.6.0 ; extra == "dev"
Requires-Dist: pyink ; extra == "dev"
Project-URL: homepage, https://github.com/google-research/precondition
Project-URL: repository, https://github.com/google-research/precondition
Provides-Extra: dev
